flake8_pylint/__init__.py
flake8_pylint/_plugin.py
flake8_pylint-0.1.3.dist-info/entry_points.txt
flake8_pylint-0.1.3.dist-info/LICENSE
flake8_pylint-0.1.3.dist-info/WHEEL
flake8_pylint-0.1.3.dist-info/METADATA
flake8_pylint-0.1.3.dist-info/RECORD
