Metadata-Version: 1.1
Name: flake8-pylint
Version: 0.1.3
Summary: Flake8 plugin that runs PyLint.
Home-page: https://github.com/orsinium-labs/flake8-pylint
Author: Gram
Author-email: gram@orsinium.dev
